{
  "date": "2026-04-06",
  "generated_at": "2026-04-06T06:46:06.099323+09:00",
  "highlight": "本日は学長からの投稿や運営からのお知らせはありませんでした。\n新しい情報がない日だからこそ、これまで得た学びをじっくり復習し、自身の行動計画を見つめ直す絶好のチャンスにしましょう！\n静かに自分と向き合い、次の行動へと活かす大切な一日です。",
  "sections": [
    {
      "title": "学長マガジン",
      "room_id": "President-Tweet",
      "summary": "本日の投稿はありませんでした",
      "post_count": 0
    },
    {
      "title": "学長ライブまとめ",
      "room_id": "LIVE-Text",
      "summary": "本日の投稿はありませんでした",
      "post_count": 0
    },
    {
      "title": "運営からのお知らせ",
      "room_id": "Liberal-City",
      "summary": "本日の投稿はありませんでした",
      "post_count": 0
    }
  ]
}