{
  "date": "2026-04-29",
  "generated_at": "2026-04-30T07:15:17.220146+09:00",
  "sections": [
    {
      "title": "学長マガジン",
      "room_id": "President-Tweet",
      "summary": "・AIが東大理3に首席合格、自己投資のあり方見直しを\n・独立志望者へ学長が助言、AIツールの使い分けも解説\n・AI時代に稼ぐ本質は変わらず、磨くべき7つのスキル提示\n・AIを活用した収入の作り方、3つの設計図を紹介",
      "post_count": 3
    },
    {
      "title": "学長ライブまとめ",
      "room_id": "LIVE-Text",
      "summary": "・AI時代に対応した副業18選を発表\n・AIを活用したD2Cブランド立ち上げを実演\n・楽天・SBIコンボと事業用カードの使い分け\n・家事按分や経費処理の基本を解説",
      "post_count": 1
    },
    {
      "title": "運営からのお知らせ",
      "room_id": "Liberal-City",
      "summary": "本日の投稿はありませんでした",
      "post_count": 0
    }
  ]
}